{
  "employees": [
    {
      "name": "Lakshmi",
      "designation": " Lead",
      "id": 4573
    },
    {
      "name": "Setna",
      "designation": "Senior Associate",
      "id": 4575
    },
    {
      "name": "Ramya",
      "designation": "Lead",
      "id": 4577
    },
    {
      "name": "Vidya Hello",
      "designation": "Lead",
      "id": 4580
    },
    {
      "name": "Kavya",
      "designation": "pappu pappu",
      "id": 4583
    },
    {
      "name": "Shilpa Chethan",
      "designation": "Manager",
      "id": 4584
    },
    {
      "name": "Venkatesh Koppar",
      "designation": "Digital Specialist Engineer",
      "id": 4585
    },
    {
      "name": "Venkatesh J Koppar",
      "designation": "Digital Specialist Engineer",
      "empId": "1235",
      "id": 4586
    },
    {
      "name": "Goutam",
      "designation": "Digital Specialist Engineer",
      "id": 4588
    }
  ]
}